[
    {
        "rowNumber": 1,
        "company": "Company",
        "name": "Name",
        "additional": "Additional",
        "street": "Street",
        "postalCode": "Postal Code",
        "country": "Country",
        "iban": "IBAN",
        "bic": "BIC",
        "bankName": "Bank Name",
        "fax": "Fax",
        "email": "E-mail",
        "birthday": "Birthday"
    },
    {
        "rowNumber": 2,
        "company": "Company",
        "name": "Name",
        "additional": "Additional",
        "street": "Street",
        "postalCode": "Postal Code",
        "country": "Country",
        "iban": "IBAN",
        "bic": "BIC",
        "bankName": "Bank Name",
        "fax": "Fax",
        "email": "E-mail",
        "birthday": "Birthday"
    }
]